Metadata-Version: 2.1
Name: pygates
Version: 0.2
Summary: With PyGates library, you can use logic gates on Python.
Home-page: https://github.com/Baticaly/PyGates
Author: Batuhan Ergün
Author-email: contact@batuhanergun.com
License: MIT
Download-URL: https://github.com/Baticaly/PyGates/archive/0.1.tar.gz
Keywords: PyGates,Python,Conditionals
Platform: UNKNOWN
Classifier: Development Status :: 3 - Alpha
Classifier: Intended Audience :: Developers
Classifier: Topic :: Software Development :: Build Tools
Classifier: License :: OSI Approved :: MIT License
Classifier: Programming Language :: Python :: 3
Classifier: Programming Language :: Python :: 3.4
Classifier: Programming Language :: Python :: 3.5
Classifier: Programming Language :: Python :: 3.6
